datascape/__init__.py
datascape/cli.py
datascape-0.0.2.dist-info/LICENSE
datascape-0.0.2.dist-info/METADATA
datascape-0.0.2.dist-info/WHEEL
datascape-0.0.2.dist-info/entry_points.txt
datascape-0.0.2.dist-info/RECORD
