Metadata-Version: 2.1
Name: datascape
Version: 0.0.2
Summary: Dataset manager
License: MIT
Author: Derek Wisong
Author-email: derekwisong@gmail.com
Requires-Python: >=3.9,<4.0
Classifier: License :: OSI Approved :: MIT License
Classifier: Programming Language :: Python :: 3
Classifier: Programming Language :: Python :: 3.9
Classifier: Programming Language :: Python :: 3.10
Classifier: Programming Language :: Python :: 3.11
Classifier: Programming Language :: Python :: 3.12
Requires-Dist: fastparquet (>=2023.10.1,<2024.0.0)
Requires-Dist: pandas (>=2.1.3,<3.0.0)
Requires-Dist: pyarrow (>=14.0.1,<15.0.0)
